{
  "conclusion": "ドル円は歴史的な円安水準を更新し、為替介入への警戒感が極めて高い状態です。米・イラン間の攻撃停止合意は原油価格の過度な上昇リスクを軽減しますが、本日発表の米雇用統計が今後の市場の方向性を決定づける主要因となるでしょう。",
  "political_news": [
    {
      "headline": "米・イラン、攻撃停止合意",
      "what_happened": "米国とイランが中東のホルムズ海峡周辺での相互攻撃を停止することで合意し、30日にカタールで高官協議を行う見通し。ただし、イラン外務省は一部報道を否定し、最終合意交渉は未着手としている。",
      "why_important": "ホルムズ海峡の安定化は原油価格の過度な高騰リスクを抑制し、米国経済のインフレ圧力緩和に寄与する。日本は原油輸入の多くを中東に依存しており、エネルギーコスト安定化への期待が高まるが、イラン側の発言で情勢の不確実性は残る。",
      "risk_level": "中",
      "source": "Reuters, NHKニュース, 時事ドットコム"
    },
    {
      "headline": "中国、対日禁輸措置を拡大",
      "what_happened": "中国商務省が、「防衛省防衛研究所」など日本の20団体や企業を輸出規制リストに追加し、軍民両用と見なされる品目の中国からの輸出を禁止すると発表した。日本の軍事力向上に関与しているとの理由。",
      "why_important": "日本企業は、軍民両用技術に関連する中国からの部品調達や中国への輸出において影響を受ける可能性がある。サプライチェーンの再編を加速させる要因となりうる地政学的リスクであり、米中対立の構図に日本が巻き込まれる側面を示す。",
      "risk_level": "中",
      "source": "時事ドットコム, NHKニュース"
    },
    {
      "headline": "米最高裁、FRB理事解任無効",
      "what_happened": "米連邦最高裁判所は、トランプ大統領（当時）がFRBのクック理事を解任すると通知したことについて、無効とする判断を示した。",
      "why_important": "FRBの独立性が司法によって再確認され、政治的な介入に対する中央銀行の防衛力が強化された形。これにより、今後の米金融政策決定プロセスにおける透明性と市場の信頼性が維持される可能性が高く、米国経済の安定に寄与すると考えられる。",
      "risk_level": "低",
      "source": "NHKニュース, BBC World"
    }
  ],
  "economic_news": [
    {
      "headline": "ドル円、39年半ぶり円安",
      "facts": "29日のニューヨーク外国為替市場で円は一時1ドル=161円90銭台後半まで値下がりし、1986年以来約39年半ぶりの円安ドル高水準をつけた。その後、急速に売りが入る場面もあった。",
      "us_market_impact": "米国ではドル高が輸入品価格を押し下げ、インフレ圧力の緩和に寄与する可能性がある。ただし、急激なドル高は米国の輸出競争力に影響を及ぼすリスクも。FRBの利上げ観測がドル高を支えている。",
      "jp_market_impact": "日本市場では輸出関連企業の収益を押し上げる一方で、輸入物価の高騰を通じて家計や企業の負担が増大。政府・日銀による為替介入への警戒感が極めて高く、市場の不安定要因となる。日銀の追加利上げ期待にも影響を与えうる。",
      "source": "NHKニュース, Reuters, 読売新聞"
    },
    {
      "headline": "日経平均に調整圧力強まる",
      "facts": "日経平均株価は小幅反発する場面もあったが、AI関連銘柄が重しとなり調整圧力が働き始めたとの指摘がある。一部では、7万円台前半での足場固めが進むとの見方も。",
      "us_market_impact": "米国市場のAI関連株（ハイテク株）の動向は、日本市場の関連銘柄にも直接影響を与える。米国でのAIバブル調整が本格化すれば、世界的なリスクオフの流れに繋がり、米国株も下落圧力に晒される可能性がある。",
      "jp_market_impact": "AI関連銘柄への依存度が高い日本株市場では、米国市場でのハイテク株調整が直接的な下落要因となる。内需株に資金がシフトする動きも見られるが、市場全体の心理は悪化しやすく、上値が重くなる可能性がある。",
      "source": "第一ライフ資産運用経済研究所, Reuters"
    },
    {
      "headline": "日銀利上げ、世論は「評価」",
      "facts": "日経世論調査によると、日銀の利上げを「評価する」が58%に対し、「評価しない」は29%だった。一方、ドル円は162円の壁と介入警戒が交錯しており、米雇用統計後の9月利上げ観測が続く。",
      "us_market_impact": "米国の金利動向は日本の金融政策に間接的に影響を与える。特に日米金利差は為替に直結するため、米国の利上げ観測はドル高円安を助長し、日本の金融政策の自由度を制約する一因となる。",
      "jp_market_impact": "日銀の利上げ判断は、国民の生活や企業活動に直接的な影響を及ぼすため、世論の動向は政策決定に少なからず影響を与えうる。為替介入への警戒感が高まる中、日銀は金融政策運営の舵取りがより難しくなっている状況。",
      "source": "日本経済新聞, 外為どっとコム"
    }
  ],
  "market_perspective": {
    "us_summary": "米国市場は、中東情勢の緩和期待とFRBの独立性維持の判断が好感され、株価は堅調に推移する可能性がある。ただし、本日発表される米雇用統計の結果次第で、9月利上げ観測が強まり、金利は上昇・ドル高基調が続く可能性がある。",
    "jp_summary": "日本市場は、ドル円の歴史的な円安進行に伴う政府・日銀による為替介入への強い警戒感と、AI関連株の調整圧力が上値を抑制する展開が予想される。一方で、円安は輸出企業の業績に追い風となり、内需株へのシフトも見られる。金利は日銀の金融政策次第で上昇圧力が継続。",
    "us_jp_linkage": "米国の金融政策（特に金利動向）と雇用統計は、日米金利差を通じてドル円相場に直接影響を与える。円安が進行すれば、日本政府・日銀による為替介入のリスクが高まり、市場のボラティリティが増大する。また、米国ハイテク株の調整は日本市場のAI関連株に波及し、日経平均の重しとなる可能性が高い。"
  }
}